{
  "name": "MyProxy",
  "type": "flogo:app",
  "version": "1.0.0",
  "description": "This is a simple proxy.",
  "properties": null,
  "channels": null,
  "triggers": [
    {
      "name": "flogo-grpc",
      "id": "MyProxy",
      "ref": "github.com/project-flogo/grpc/trigger/grpc",
      "settings": {
        "port": "9096",
        "protoName": "petstore"
      },
      "handlers": [
        {
          "settings": {
            "serviceName": "GRPC2RestPetStoreService",
            "methodName": "PetById"
          },
          "actions": [
            {
              "id": "microgateway:petByIdDispatch"
            }
          ]
        },
        {
          "settings": {
            "serviceName": "GRPC2RestPetStoreService",
            "methodName": "PetPUT"
          },
          "actions": [
            {
              "id": "microgateway:petPutDispatch"
            }
          ]
        },
        {
          "settings": {
            "serviceName": "GRPC2RestPetStoreService",
            "methodName": "UserByName"
          },
          "actions": [
            {
              "id": "microgateway:userByNameDispatch"
            }
          ]
        }
      ]
    }
  ],
  "resources": [
    {
      "id": "microgateway:petByIdDispatch",
      "compressed": false,
      "data": {
        "name": "Pets",
        "steps": [
          {
            "service": "PetStorePets",
            "input": {
              "pathParams.id": "=$.payload.params.id"
            }
          }
        ],
        "responses": [
          {
            "if": "$.PetStorePets.outputs.data.type == 'error'",
            "error": true,
            "output": {
              "code": 404,
              "data": {
                "error": "=$.PetStorePets.outputs.data.message"
              }
            }
          },
          {
            "if": "$.PetStorePets.outputs.data.type != 'error'",
            "error": false,
            "output": {
              "code": 200,
              "data": {
                "pet": "=$.PetStorePets.outputs.data"
              }
            }
          }
        ],
        "services": [
          {
            "name": "PetStorePets",
            "description": "Make calls to find pets",
            "ref": "github.com/project-flogo/contrib/activity/rest",
            "settings": {
              "uri": "http://petstore.swagger.io/v2/pet/:id",
              "method": "GET"
            }
          }
        ]
      }
    },
    {
      "id": "microgateway:petPutDispatch",
      "compressed": false,
      "data": {
        "name": "Pets",
        "steps": [
          {
            "service": "PetStorePetsPUT",
            "input": {
              "content": "=$.payload.content"
            }
          }
        ],
        "responses": [
          {
            "if": "$.PetStorePetsPUT.outputs.data.type == 'error'",
            "error": true,
            "output": {
              "code": 404,
              "data": {
                "error": "=$.PetStorePetsPUT.outputs.data.message"
              }
            }
          },
          {
            "if": "$.PetStorePetsPUT.outputs.data.type != 'error'",
            "error": false,
            "output": {
              "code": 200,
              "data": {
                "pet": "=$.PetStorePetsPUT.outputs.data"
              }
            }
          }
        ],
        "services": [
          {
            "name": "PetStorePetsPUT",
            "description": "Make calls to petstore",
            "ref": "github.com/project-flogo/contrib/activity/rest",
            "settings": {
              "uri": "http://petstore.swagger.io/v2/pet",
              "method": "PUT",
              "headers": {
                "Content-Type": "application/json"
              }
            }
          }
        ]
      }
    },
    {
      "id": "microgateway:userByNameDispatch",
      "compressed": false,
      "data": {
        "name": "Pets",
        "steps": [
          {
            "service": "PetStoreUsersByName",
            "input": {
              "pathParams.username": "=$.payload.params.username"
            }
          }
        ],
        "responses": [
          {
            "if": "$.PetStoreUsersByName.outputs.data.type == 'error'",
            "error": true,
            "output": {
              "code": 404,
              "data": {
                "error": "=$.PetStoreUsersByName.outputs.data.message"
              }
            }
          },
          {
            "if": "$.PetStoreUsersByName.outputs.data.type != 'error'",
            "error": false,
            "output": {
              "code": 200,
              "data": {
                "user": "=$.PetStoreUsersByName.outputs.data"
              }
            }
          }
        ],
        "services": [
          {
            "name": "PetStoreUsersByName",
            "description": "Make calls to find users",
            "ref": "github.com/project-flogo/contrib/activity/rest",
            "settings": {
              "uri": "http://petstore.swagger.io/v2/user/:username",
              "method": "GET"
            }
          }
        ]
      }
    }
  ],
  "actions": [
    {
      "ref": "github.com/project-flogo/microgateway",
      "settings": {
        "uri": "microgateway:petByIdDispatch"
      },
      "id": "microgateway:petByIdDispatch",
      "metadata": null
    },
    {
      "ref": "github.com/project-flogo/microgateway",
      "settings": {
        "uri": "microgateway:petPutDispatch"
      },
      "id": "microgateway:petPutDispatch",
      "metadata": null
    },
    {
      "ref": "github.com/project-flogo/microgateway",
      "settings": {
        "uri": "microgateway:userByNameDispatch"
      },
      "id": "microgateway:userByNameDispatch",
      "metadata": null
    }
  ]
}
